yamlimg/__init__.py
yamlimg/__main__.py
yamlimg/cli/__init__.py
yamlimg/impl/__init__.py
yamlimg/impl/converter.py
yamlimg/impl/spec.py
yamlimg-1.0.2.dist-info/entry_points.txt
yamlimg-1.0.2.dist-info/LICENSE
yamlimg-1.0.2.dist-info/WHEEL
yamlimg-1.0.2.dist-info/METADATA
yamlimg-1.0.2.dist-info/RECORD
