Metadata-Version: 2.1
Name: yamlimg
Version: 1.0.2
Summary: A way to store images in YAML.
Home-page: https://github.com/vcokltfre/yamlimg
License: MIT
Keywords: yaml,image,storage
Author: vcokltfre
Author-email: vcokltfre@gmail.com
Requires-Python: >=3.8,<4.0
Classifier: License :: OSI Approved :: MIT License
Classifier: Programming Language :: Python :: 3
Classifier: Programming Language :: Python :: 3.10
Classifier: Programming Language :: Python :: 3.8
Classifier: Programming Language :: Python :: 3.9
Requires-Dist: Pillow (>=9.0.1,<10.0.0)
Requires-Dist: PyYAML (>=6.0,<7.0)
Requires-Dist: pydantic (>=1.9.0,<2.0.0)
Requires-Dist: typer (>=0.4.0,<0.5.0)
Project-URL: Repository, https://github.com/vcokltfre/yamlimg
